plover_qmk/__init__.py
plover_qmk/find_dev.py
plover_qmk/hidapi_backend.py
plover_qmk/hiddev.py
plover_qmk/linux_backend.py
plover_stenohid_test-0.1.0.dev2.dist-info/DESCRIPTION.rst
plover_stenohid_test-0.1.0.dev2.dist-info/METADATA
plover_stenohid_test-0.1.0.dev2.dist-info/RECORD
plover_stenohid_test-0.1.0.dev2.dist-info/WHEEL
plover_stenohid_test-0.1.0.dev2.dist-info/entry_points.txt
plover_stenohid_test-0.1.0.dev2.dist-info/metadata.json
plover_stenohid_test-0.1.0.dev2.dist-info/top_level.txt
